alexa_skill_kit
